LICENSE.txt
README.md
setup.py
E897SHIELD/__init__.py
E897SHIELD/a1.py
E897SHIELD.egg-info/PKG-INFO
E897SHIELD.egg-info/SOURCES.txt
E897SHIELD.egg-info/dependency_links.txt
E897SHIELD.egg-info/requires.txt
E897SHIELD.egg-info/top_level.txt